typesvalidator/__init__.py
typesvalidator/typesvalidator.py
typesvalidator-0.0.3.dist-info/LICENSE
typesvalidator-0.0.3.dist-info/METADATA
typesvalidator-0.0.3.dist-info/WHEEL
typesvalidator-0.0.3.dist-info/top_level.txt
typesvalidator-0.0.3.dist-info/RECORD
